Brestart2/__init__.py
Brestart2-0.1.dist-info/LICENSE
Brestart2-0.1.dist-info/METADATA
Brestart2-0.1.dist-info/WHEEL
Brestart2-0.1.dist-info/top_level.txt
Brestart2-0.1.dist-info/RECORD
