Metadata-Version: 2.1
Name: Brestart2
Version: 0.1
Summary: restart functions at breakpoint
Home-page: https://github.com/lvws/python-breakpoint-restart-Python-
Author: Wansheng.Lv
Author-email: 1129309258@qq.com
License: MIT
Platform: UNKNOWN
Classifier: Programming Language :: Python :: 3
Classifier: License :: OSI Approved :: MIT License
Classifier: Operating System :: OS Independent
Requires-Python: >=3.4
